[
  {
    "title": "62岁崔永元罕见现身",
    "content": "62岁崔永元罕见现身",
    "source_platform": "腾讯娱乐",
    "timestamp": "2026-01-25T22:23:23.203590"
  },
  {
    "title": "赵学煌追悼会众星送别",
    "content": "赵学煌追悼会众星送别",
    "source_platform": "腾讯娱乐",
    "timestamp": "2026-01-25T22:23:23.203596"
  },
  {
    "title": "《翠湖》到底拍出了什么真相？",
    "content": "《翠湖》到底拍出了什么真相？",
    "source_platform": "腾讯娱乐",
    "timestamp": "2026-01-25T22:23:23.203598"
  },
  {
    "title": "75岁刘晓庆再扮嫩与男演员拍吻戏",
    "content": "75岁刘晓庆再扮嫩与男演员拍吻戏",
    "source_platform": "腾讯娱乐",
    "timestamp": "2026-01-25T22:23:23.203599"
  },
  {
    "title": "脱口秀演员王越自曝患甲状腺癌",
    "content": "脱口秀演员王越自曝患甲状腺癌",
    "source_platform": "腾讯娱乐",
    "timestamp": "2026-01-25T22:23:23.203600"
  },
  {
    "title": "北京将新增3.5万个机动车停车位",
    "content": "北京将新增3.5万个机动车停车位",
    "source_platform": "抖音热榜",
    "timestamp": "2026-01-25T22:23:23.203601"
  },
  {
    "title": "辽篮客场不敌新疆男篮遭四连败",
    "content": "辽篮客场不敌新疆男篮遭四连败",
    "source_platform": "抖音热榜",
    "timestamp": "2026-01-25T22:23:23.203602"
  },
  {
    "title": "中国卫星技术全球顶流",
    "content": "中国卫星技术全球顶流",
    "source_platform": "抖音热榜",
    "timestamp": "2026-01-25T22:23:23.203604"
  },
  {
    "title": "中国海警向菲方移交获救菲籍人员",
    "content": "中国海警向菲方移交获救菲籍人员",
    "source_platform": "抖音热榜",
    "timestamp": "2026-01-25T22:23:23.203605"
  },
  {
    "title": "黄晓明Baby离婚后带儿子游迪士尼",
    "content": "黄晓明Baby离婚后带儿子游迪士尼",
    "source_platform": "腾讯娱乐",
    "timestamp": "2026-01-26T06:31:57.859097"
  },
  {
    "title": "张雨绮被前夫前妻实名举报",
    "content": "张雨绮被前夫前妻实名举报",
    "source_platform": "腾讯娱乐",
    "timestamp": "2026-01-26T06:31:57.859103"
  },
  {
    "title": "梁小龙追悼会举行周星驰送花圈",
    "content": "梁小龙追悼会举行周星驰送花圈",
    "source_platform": "腾讯娱乐",
    "timestamp": "2026-01-26T06:31:57.859105"
  },
  {
    "title": "向太喊话李亚鹏“放过自己”",
    "content": "向太喊话李亚鹏“放过自己”",
    "source_platform": "腾讯娱乐",
    "timestamp": "2026-01-26T06:31:57.859106"
  },
  {
    "title": "戚薇一家四口看演唱会",
    "content": "戚薇一家四口看演唱会",
    "source_platform": "腾讯娱乐",
    "timestamp": "2026-01-26T06:31:57.859107"
  },
  {
    "title": "何健麒前女友再回应举报涉毒：愿接受核查",
    "content": "何健麒前女友再回应举报涉毒：愿接受核查",
    "source_platform": "腾讯娱乐",
    "timestamp": "2026-01-26T06:31:57.859108"
  },
  {
    "title": "陈汉典Lulu举办婚礼",
    "content": "陈汉典Lulu举办婚礼",
    "source_platform": "腾讯娱乐",
    "timestamp": "2026-01-26T06:31:57.859109"
  },
  {
    "title": "专项资金为电影高质量发展赋能",
    "content": "专项资金为电影高质量发展赋能",
    "source_platform": "抖音热榜",
    "timestamp": "2026-01-26T06:31:57.859110"
  },
  {
    "title": "英媒：英国首相周二访华",
    "content": "英媒：英国首相周二访华",
    "source_platform": "抖音热榜",
    "timestamp": "2026-01-26T06:31:57.859112"
  },
  {
    "title": "孙涛宣布不再参加春晚",
    "content": "孙涛宣布不再参加春晚",
    "source_platform": "腾讯娱乐",
    "timestamp": "2026-01-26T10:41:21.688560"
  },
  {
    "title": "三毛扮演者孟智超回应拍短剧",
    "content": "三毛扮演者孟智超回应拍短剧",
    "source_platform": "腾讯娱乐",
    "timestamp": "2026-01-26T10:41:21.688566"
  },
  {
    "title": "林俊杰七七公布恋情后首同框看电影",
    "content": "林俊杰七七公布恋情后首同框看电影",
    "source_platform": "腾讯娱乐",
    "timestamp": "2026-01-26T10:41:21.688568"
  },
  {
    "title": "电影《翠湖》终极预告",
    "content": "电影《翠湖》终极预告",
    "source_platform": "腾讯娱乐",
    "timestamp": "2026-01-26T10:41:21.688569"
  },
  {
    "title": "“性商教母”只能割女人韭菜",
    "content": "“性商教母”只能割女人韭菜",
    "source_platform": "腾讯娱乐",
    "timestamp": "2026-01-26T10:41:21.688570"
  },
  {
    "title": "82岁老师写高考作文引关注",
    "content": "82岁老师写高考作文引关注",
    "source_platform": "抖音热榜",
    "timestamp": "2026-01-26T10:41:21.688571"
  },
  {
    "title": "年味争霸赛开赛啦",
    "content": "年味争霸赛开赛啦",
    "source_platform": "抖音热榜",
    "timestamp": "2026-01-26T10:41:21.688572"
  },
  {
    "title": "杨鸣辞任辽篮主帅",
    "content": "杨鸣辞任辽篮主帅",
    "source_platform": "抖音热榜",
    "timestamp": "2026-01-26T10:41:21.688574"
  },
  {
    "title": "国安部提示警惕“带节奏”手段",
    "content": "国安部提示警惕“带节奏”手段",
    "source_platform": "抖音热榜",
    "timestamp": "2026-01-26T10:41:21.688575"
  },
  {
    "title": "《小城大事》大结局",
    "content": "《小城大事》大结局",
    "source_platform": "腾讯娱乐",
    "timestamp": "2026-01-26T22:24:32.737859"
  },
  {
    "title": "鲁豫范晓萱拒绝浪姐的原因",
    "content": "鲁豫范晓萱拒绝浪姐的原因",
    "source_platform": "腾讯娱乐",
    "timestamp": "2026-01-26T22:24:32.737866"
  },
  {
    "title": "张雨绮被曝知三当三，辽视春晚节目被删",
    "content": "张雨绮被曝知三当三，辽视春晚节目被删",
    "source_platform": "腾讯娱乐",
    "timestamp": "2026-01-26T22:24:32.737867"
  },
  {
    "title": "陈星旭自曝三个月不发朋友圈",
    "content": "陈星旭自曝三个月不发朋友圈",
    "source_platform": "腾讯娱乐",
    "timestamp": "2026-01-26T22:24:32.737868"
  },
  {
    "title": "外交部提醒春节避免前往日本",
    "content": "外交部提醒春节避免前往日本",
    "source_platform": "抖音热榜",
    "timestamp": "2026-01-26T22:24:32.737869"
  },
  {
    "title": "国投白银LOF将暂停申购",
    "content": "国投白银LOF将暂停申购",
    "source_platform": "抖音热榜",
    "timestamp": "2026-01-26T22:24:32.737869"
  },
  {
    "title": "全国机动车保有量达4.69亿辆",
    "content": "全国机动车保有量达4.69亿辆",
    "source_platform": "抖音热榜",
    "timestamp": "2026-01-26T22:24:32.737870"
  },
  {
    "title": "尼帕病毒令赴泰游客进退两难",
    "content": "尼帕病毒令赴泰游客进退两难",
    "source_platform": "抖音热榜",
    "timestamp": "2026-01-26T22:24:32.737872"
  },
  {
    "title": "甘肃甘南5.5级地震",
    "content": "甘肃甘南5.5级地震",
    "source_platform": "抖音热榜",
    "timestamp": "2026-01-26T22:24:32.737873"
  }
]